jaac/__init__.py
jaac/documents/cv.tex.template.example
jaac/documents/jaac.config.toml.example
jaac/documents/letter.tex.template.example
jaac/documents/profile.txt.example
jaac/llm.py
jaac/pdf.py
jaac-0.2.3.dist-info/METADATA
jaac-0.2.3.dist-info/WHEEL
jaac-0.2.3.dist-info/entry_points.txt
jaac-0.2.3.dist-info/RECORD
