Metadata-Version: 2.1
Name: jaac
Version: 0.2.3
Summary: Job Application Assets Creator
Home-page: https://github.com/jonapellet/JAAC
License: MIT
Author: Jonathan Pelletier
Author-email: jonathan.pelletier-aafz@thecloudco.ca
Requires-Python: >=3.11,<4.0
Classifier: License :: OSI Approved :: MIT License
Classifier: Programming Language :: Python :: 3
Classifier: Programming Language :: Python :: 3.11
Classifier: Programming Language :: Python :: 3.12
Requires-Dist: click (>=8.1.7,<9.0.0)
Requires-Dist: jinja2 (>=3.1.4,<4.0.0)
Requires-Dist: openai (>=1.26.0,<2.0.0)
Project-URL: Repository, https://github.com/jonapellet/JAAC
